{
  "subjectId": 642407,
  "trackCredits": {
    "1.1": {
      "composer": [
        {
          "type": "person",
          "person": {
            "ref": null,
            "text": "CULT P"
          }
        }
      ],
      "mixing": [
        {
          "type": "person",
          "person": {
            "ref": null,
            "text": "um."
          }
        }
      ]
    },
    "1.2": {
      "composer": [
        {
          "type": "person",
          "person": {
            "ref": null,
            "text": "砂粒"
          }
        }
      ],
      "mixing": [
        {
          "type": "person",
          "person": {
            "ref": null,
            "text": "哀"
          }
        }
      ]
    },
    "1.3": {
      "composer": [
        {
          "type": "person",
          "person": {
            "ref": null,
            "text": "九七."
          }
        }
      ],
      "mixing": [
        {
          "type": "person",
          "person": {
            "ref": null,
            "text": "um."
          }
        }
      ]
    },
    "1.10": {
      "composer": [
        {
          "type": "person",
          "person": {
            "ref": null,
            "text": "九七."
          }
        }
      ],
      "mixing": [
        {
          "type": "person",
          "person": {
            "ref": null,
            "text": "哀"
          }
        }
      ]
    },
    "1.6": {
      "composer": [
        {
          "type": "person",
          "person": {
            "ref": null,
            "text": "N1N63N"
          }
        }
      ],
      "mixing": [
        {
          "type": "person",
          "person": {
            "ref": null,
            "text": "um."
          }
        }
      ]
    },
    "1.7": {
      "composer": [
        {
          "type": "person",
          "person": {
            "ref": null,
            "text": "Layca"
          }
        }
      ],
      "mixing": [
        {
          "type": "person",
          "person": {
            "ref": null,
            "text": "哀"
          }
        }
      ]
    },
    "1.8": {
      "composer": [
        {
          "type": "person",
          "person": {
            "ref": null,
            "text": "凍傷のエト"
          }
        }
      ],
      "mixing": [
        {
          "type": "person",
          "person": {
            "ref": null,
            "text": "哀"
          }
        }
      ]
    },
    "1.12": {
      "chorus": [
        {
          "type": "person",
          "person": {
            "ref": null,
            "text": "越前"
          }
        }
      ],
      "mixing": [
        {
          "type": "person",
          "person": {
            "ref": null,
            "text": "哀"
          }
        }
      ]
    },
    "1.4": {
      "mixing": [
        {
          "type": "person",
          "person": {
            "ref": null,
            "text": "um."
          }
        }
      ]
    },
    "1.9": {
      "mixing": [
        {
          "type": "person",
          "person": {
            "ref": null,
            "text": "um."
          }
        }
      ]
    },
    "1.5": {
      "mixing": [
        {
          "type": "person",
          "person": {
            "ref": null,
            "text": "哀"
          }
        }
      ]
    },
    "1.11": {
      "mixing": [
        {
          "type": "person",
          "person": {
            "ref": null,
            "text": "哀"
          }
        }
      ]
    }
  },
  "rawPatches": {
    "editor": "作曲：CULT P(1)、砂粒(2)、九七.(3,10)、N1N63N(6)、Layca(7)、凍傷のエト(8)\n声乐：越前(12)\n混音：um.(1,3,4,6,9)、哀(2,5,7,8,10,11,12)"
  },
  "_meta": {
    "submittedBy": "459115",
    "submittedUserGroup": 11,
    "submittedAt": "2026-04-18T14:21:16.017Z"
  }
}
