{
  "subjectId": 643003,
  "trackCredits": {
    "1.1": {
      "artist": [
        {
          "type": "person",
          "person": {
            "ref": null,
            "text": "サタスコ"
          }
        }
      ]
    },
    "1.2": {
      "artist": [
        {
          "type": "person",
          "person": {
            "ref": null,
            "text": "カワムラシキ"
          }
        }
      ]
    },
    "1.3": {
      "artist": [
        {
          "type": "person",
          "person": {
            "ref": null,
            "text": "Ruliea"
          }
        }
      ]
    },
    "1.4": {
      "artist": [
        {
          "type": "person",
          "person": {
            "ref": null,
            "text": "夜丹れにや"
          }
        }
      ]
    },
    "1.5": {
      "artist": [
        {
          "type": "person",
          "person": {
            "ref": null,
            "text": "Ichinoku"
          }
        }
      ]
    },
    "1.7": {
      "artist": [
        {
          "type": "person",
          "person": {
            "ref": null,
            "text": "桶屋"
          }
        }
      ]
    },
    "1.9": {
      "artist": [
        {
          "type": "person",
          "person": {
            "ref": null,
            "text": "みずな"
          }
        }
      ]
    }
  },
  "rawPatches": {
    "editor": "艺术家：サタスコ(1)、カワムラシキ(2)、Ruliea(3)、夜丹れにや(4)、Ichinoku(5)、桶屋(7)、みずな(9)"
  },
  "_meta": {
    "submittedBy": "459115",
    "submittedUserGroup": 11,
    "submittedAt": "2026-04-21T06:17:35.438Z"
  }
}
