{
  "subjectId": 643663,
  "trackCredits": {
    "1.2": {
      "artist": [
        {
          "type": "person",
          "person": {
            "ref": null,
            "text": "Nicho"
          }
        }
      ]
    },
    "1.3": {
      "artist": [
        {
          "type": "person",
          "person": {
            "ref": null,
            "text": "Zhenz"
          }
        }
      ]
    },
    "1.4": {
      "artist": [
        {
          "type": "person",
          "person": {
            "ref": null,
            "text": "AntonFer"
          }
        }
      ]
    },
    "1.5": {
      "artist": [
        {
          "type": "person",
          "person": {
            "ref": null,
            "text": "Qbod"
          }
        }
      ]
    },
    "1.6": {
      "artist": [
        {
          "type": "person",
          "person": {
            "ref": null,
            "text": "Apin17"
          }
        }
      ]
    },
    "1.7": {
      "artist": [
        {
          "type": "person",
          "person": {
            "ref": null,
            "text": "Endro Chan"
          }
        }
      ]
    },
    "1.8": {
      "artist": [
        {
          "type": "person",
          "person": {
            "ref": null,
            "text": "RN"
          }
        }
      ]
    },
    "1.9": {
      "artist": [
        {
          "type": "person",
          "person": {
            "ref": null,
            "text": "Dimitar"
          }
        }
      ]
    },
    "1.10": {
      "artist": [
        {
          "type": "person",
          "person": {
            "ref": null,
            "text": "Surya Groxyn"
          }
        }
      ]
    }
  },
  "rawPatches": {
    "editor": "艺术家：Nicho(2)、Zhenz(3)、AntonFer(4)、Qbod(5)、Apin17(6)、Endro Chan(7)、RN(8)、Dimitar(9)、Surya Groxyn(10)"
  },
  "_meta": {
    "submittedBy": "459115",
    "submittedUserGroup": 11,
    "submittedAt": "2026-04-23T04:52:18.255Z"
  }
}
